MANIFEST.in
README.rst
setup.py
nacelle/__init__.py
nacelle/app.py
nacelle.egg-info/PKG-INFO
nacelle.egg-info/SOURCES.txt
nacelle.egg-info/dependency_links.txt
nacelle.egg-info/not-zip-safe
nacelle.egg-info/top_level.txt
nacelle/conf/__init__.py
nacelle/conf/default_settings.py
nacelle/contrib/__init__.py
nacelle/contrib/lockdown/__init__.py
nacelle/contrib/lockdown/decorators.py
nacelle/contrib/lockdown/dispatcher.py
nacelle/contrib/lockdown/mixins.py
nacelle/contrib/lockdown/tests.py
nacelle/contrib/lockdown/utils.py
nacelle/contrib/mail/__init__.py
nacelle/contrib/mail/handlers.py
nacelle/contrib/mail/interface.py
nacelle/contrib/mail/routes.py
nacelle/contrib/mail/tests.py
nacelle/contrib/mail/utils.py
nacelle/core/__init__.py
nacelle/core/decorators.py
nacelle/core/dispatcher.py
nacelle/core/exception_handlers.py
nacelle/core/routes.py
nacelle/core/sessions/__init__.py
nacelle/core/sessions/models.py
nacelle/core/sessions/utils.py
nacelle/core/template/__init__.py
nacelle/core/template/renderers.py
nacelle/core/utils/__init__.py
nacelle/core/utils/crypto.py
nacelle/core/utils/encoder.py
nacelle/core/utils/exceptions.py
nacelle/core/utils/i18n.py
nacelle/core/utils/memoize.py
nacelle/test/__init__.py
nacelle/test/environ.py
nacelle/test/runner.py
nacelle/test/testcases.py