Metadata-Version: 1.1
Name: nacelle
Version: 0.4.0
Summary: A lightweight Python framework (built on top of webapp2) for use on Google Appengine
Home-page: https://github.com/nacelle/nacelle
Author: Patrick Carey
Author-email: patrick@rehabstudio.com
License: MIT
Keywords: nacelle
Platform: UNKNOWN
Classifier: Development Status :: 4 - Beta
Classifier: Intended Audience :: Developers
Classifier: License :: OSI Approved :: MIT License
Classifier: Natural Language :: English
Classifier: Programming Language :: Python :: 2
Classifier: Programming Language :: Python :: 2.7
